{"elements":{"nodes":[{"data":{"id":"org.jhotdraw.samples.color","properties":{"simpleName":"color","kind":"package","metaSrc":"source code"},"labels":["Container"]}},{"data":{"id":"org.jhotdraw.beans","properties":{"simpleName":"beans","kind":"package","metaSrc":"source code"},"labels":["Container"]}},{"data":{"id":"org","properties":{"simpleName":"org","kind":"package","metaSrc":"source code"},"labels":["Container"]}},{"data":{"id":"org.jhotdraw.samples.odg.figures","properties":{"simpleName":"figures","kind":"package","metaSrc":"source code"},"labels":["Container"]}},{"data":{"id":"org.jhotdraw.util","properties":{"simpleName":"util","kind":"package","metaSrc":"source code"},"labels":["Container"]}},{"data":{"id":"org.jhotdraw.draw.locator","properties":{"simpleName":"locator","kind":"package","metaSrc":"source code"},"labels":["Container"]}},{"data":{"id":"org.jhotdraw.draw.gui","properties":{"simpleName":"gui","kind":"package","metaSrc":"source code"},"labels":["Container"]}},{"data":{"id":"org.jhotdraw.gui.event","properties":{"simpleName":"event","kind":"package","metaSrc":"source code"},"labels":["Container"]}},{"data":{"id":"org.jhotdraw.samples.odg.geom","properties":{"simpleName":"geom","kind":"package","metaSrc":"source code"},"labels":["Container"]}},{"data":{"id":"org.jhotdraw.xml.css","properties":{"simpleName":"css","kind":"package","metaSrc":"source code"},"labels":["Container"]}},{"data":{"id":"org.jhotdraw.samples.teddy","properties":{"simpleName":"teddy","kind":"package","metaSrc":"source code"},"labels":["Container"]}},{"data":{"id":"org.jhotdraw.draw","properties":{"simpleName":"draw","kind":"package","metaSrc":"source code"},"labels":["Container"]}},{"data":{"id":"org.jhotdraw.samples.teddy.regex","properties":{"simpleName":"regex","kind":"package","metaSrc":"source code"},"labels":["Container"]}},{"data":{"id":"org.jhotdraw.draw.layouter","properties":{"simpleName":"layouter","kind":"package","metaSrc":"source code"},"labels":["Container"]}},{"data":{"id":"org.jhotdraw.samples.pert","properties":{"simpleName":"pert","kind":"package","metaSrc":"source code"},"labels":["Container"]}},{"data":{"id":"org.jhotdraw.samples","properties":{"simpleName":"samples","kind":"package","metaSrc":"source code"},"labels":["Container"]}},{"data":{"id":"org.jhotdraw.draw.liner","properties":{"simpleName":"liner","kind":"package","metaSrc":"source code"},"labels":["Container"]}},{"data":{"id":"org.jhotdraw.samples.net.figures","properties":{"simpleName":"figures","kind":"package","metaSrc":"source code"},"labels":["Container"]}},{"data":{"id":"org.jhotdraw.draw.connector","properties":{"simpleName":"connector","kind":"package","metaSrc":"source code"},"labels":["Container"]}},{"data":{"id":"org.jhotdraw.color","properties":{"simpleName":"color","kind":"package","metaSrc":"source code"},"labels":["Container"]}},{"data":{"id":"org.jhotdraw.samples.net","properties":{"simpleName":"net","kind":"package","metaSrc":"source code"},"labels":["Container"]}},{"data":{"id":"org.jhotdraw.samples.svg.action","properties":{"simpleName":"action","kind":"package","metaSrc":"source code"},"labels":["Container"]}},{"data":{"id":"org.jhotdraw.app.action.view","properties":{"simpleName":"view","kind":"package","metaSrc":"source code"},"labels":["Container"]}},{"data":{"id":"org.jhotdraw.gui.plaf","properties":{"simpleName":"plaf","kind":"package","metaSrc":"source code"},"labels":["Container"]}},{"data":{"id":"org.jhotdraw.xml","properties":{"simpleName":"xml","kind":"package","metaSrc":"source code"},"labels":["Container"]}},{"data":{"id":"net","properties":{"simpleName":"net","kind":"package","metaSrc":"source code"},"labels":["Container"]}},{"data":{"id":"org.jhotdraw.samples.teddy.io","properties":{"simpleName":"io","kind":"package","metaSrc":"source code"},"labels":["Container"]}},{"data":{"id":"org.jhotdraw.draw.print","properties":{"simpleName":"print","kind":"package","metaSrc":"source code"},"labels":["Container"]}},{"data":{"id":"org.jhotdraw.draw.tool","properties":{"simpleName":"tool","kind":"package","metaSrc":"source code"},"labels":["Container"]}},{"data":{"id":"org.jhotdraw.samples.odg","properties":{"simpleName":"odg","kind":"package","metaSrc":"source code"},"labels":["Container"]}},{"data":{"id":"org.jhotdraw.app.action.edit","properties":{"simpleName":"edit","kind":"package","metaSrc":"source code"},"labels":["Container"]}},{"data":{"id":"org.jhotdraw.io","properties":{"simpleName":"io","kind":"package","metaSrc":"source code"},"labels":["Container"]}},{"data":{"id":"org.jhotdraw.draw.event","properties":{"simpleName":"event","kind":"package","metaSrc":"source code"},"labels":["Container"]}},{"data":{"id":"org.jhotdraw.draw.handle","properties":{"simpleName":"handle","kind":"package","metaSrc":"source code"},"labels":["Container"]}},{"data":{"id":"org.jhotdraw.samples.svg","properties":{"simpleName":"svg","kind":"package","metaSrc":"source code"},"labels":["Container"]}},{"data":{"id":"net.n3","properties":{"simpleName":"n3","kind":"package","metaSrc":"source code"},"labels":["Container"]}},{"data":{"id":"org.jhotdraw","properties":{"simpleName":"jhotdraw","kind":"package","metaSrc":"source code"},"labels":["Container"]}},{"data":{"id":"org.jhotdraw.geom","properties":{"simpleName":"geom","kind":"package","metaSrc":"source code"},"labels":["Container"]}},{"data":{"id":"org.jhotdraw.samples.mini","properties":{"simpleName":"mini","kind":"package","metaSrc":"source code"},"labels":["Container"]}},{"data":{"id":"org.jhotdraw.draw.text","properties":{"simpleName":"text","kind":"package","metaSrc":"source code"},"labels":["Container"]}},{"data":{"id":"org.jhotdraw.app.action","properties":{"simpleName":"action","kind":"package","metaSrc":"source code"},"labels":["Container"]}},{"data":{"id":"org.jhotdraw.samples.font","properties":{"simpleName":"font","kind":"package","metaSrc":"source code"},"labels":["Container"]}},{"data":{"id":"org.jhotdraw.app.action.file","properties":{"simpleName":"file","kind":"package","metaSrc":"source code"},"labels":["Container"]}},{"data":{"id":"org.jhotdraw.samples.odg.io","properties":{"simpleName":"io","kind":"package","metaSrc":"source code"},"labels":["Container"]}},{"data":{"id":"org.jhotdraw.app.action.app","properties":{"simpleName":"app","kind":"package","metaSrc":"source code"},"labels":["Container"]}},{"data":{"id":"org.jhotdraw.util.prefs","properties":{"simpleName":"prefs","kind":"package","metaSrc":"source code"},"labels":["Container"]}},{"data":{"id":"org.jhotdraw.samples.svg.io","properties":{"simpleName":"io","kind":"package","metaSrc":"source code"},"labels":["Container"]}},{"data":{"id":"org.jhotdraw.app","properties":{"simpleName":"app","kind":"package","metaSrc":"source code"},"labels":["Container"]}},{"data":{"id":"org.jhotdraw.samples.teddy.action","properties":{"simpleName":"action","kind":"package","metaSrc":"source code"},"labels":["Container"]}},{"data":{"id":"org.jhotdraw.app.osx","properties":{"simpleName":"osx","kind":"package","metaSrc":"source code"},"labels":["Container"]}},{"data":{"id":"org.jhotdraw.gui.plaf.palette.colorchooser","properties":{"simpleName":"colorchooser","kind":"package","metaSrc":"source code"},"labels":["Container"]}},{"data":{"id":"org.jhotdraw.samples.svg.gui","properties":{"simpleName":"gui","kind":"package","metaSrc":"source code"},"labels":["Container"]}},{"data":{"id":"org.jhotdraw.draw.io","properties":{"simpleName":"io","kind":"package","metaSrc":"source code"},"labels":["Container"]}},{"data":{"id":"org.jhotdraw.gui.plaf.palette","properties":{"simpleName":"palette","kind":"package","metaSrc":"source code"},"labels":["Container"]}},{"data":{"id":"net.n3.nanoxml","properties":{"simpleName":"nanoxml","kind":"package","metaSrc":"source code"},"labels":["Container"]}},{"data":{"id":"org.jhotdraw.samples.pert.figures","properties":{"simpleName":"figures","kind":"package","metaSrc":"source code"},"labels":["Container"]}},{"data":{"id":"org.jhotdraw.net","properties":{"simpleName":"net","kind":"package","metaSrc":"source code"},"labels":["Container"]}},{"data":{"id":"org.jhotdraw.gui","properties":{"simpleName":"gui","kind":"package","metaSrc":"source code"},"labels":["Container"]}},{"data":{"id":"org.jhotdraw.gui.datatransfer","properties":{"simpleName":"datatransfer","kind":"package","metaSrc":"source code"},"labels":["Container"]}},{"data":{"id":"org.jhotdraw.undo","properties":{"simpleName":"undo","kind":"package","metaSrc":"source code"},"labels":["Container"]}},{"data":{"id":"org.jhotdraw.text","properties":{"simpleName":"text","kind":"package","metaSrc":"source code"},"labels":["Container"]}},{"data":{"id":"org.jhotdraw.samples.odg.action","properties":{"simpleName":"action","kind":"package","metaSrc":"source code"},"labels":["Container"]}},{"data":{"id":"org.jhotdraw.samples.svg.figures","properties":{"simpleName":"figures","kind":"package","metaSrc":"source code"},"labels":["Container"]}},{"data":{"id":"org.jhotdraw.samples.teddy.text","properties":{"simpleName":"text","kind":"package","metaSrc":"source code"},"labels":["Container"]}},{"data":{"id":"org.jhotdraw.draw.decoration","properties":{"simpleName":"decoration","kind":"package","metaSrc":"source code"},"labels":["Container"]}},{"data":{"id":"org.jhotdraw.gui.filechooser","properties":{"simpleName":"filechooser","kind":"package","metaSrc":"source code"},"labels":["Container"]}},{"data":{"id":"org.jhotdraw.draw.action","properties":{"simpleName":"action","kind":"package","metaSrc":"source code"},"labels":["Container"]}},{"data":{"id":"org.jhotdraw.samples.draw","properties":{"simpleName":"draw","kind":"package","metaSrc":"source code"},"labels":["Container"]}},{"data":{"id":"org.jhotdraw.gui.fontchooser","properties":{"simpleName":"fontchooser","kind":"package","metaSrc":"source code"},"labels":["Container"]}},{"data":{"id":"org.jhotdraw.app.action.window","properties":{"simpleName":"window","kind":"package","metaSrc":"source code"},"labels":["Container"]}}],"edges":[{"data":{"id":"b0a4423af1beb65aedc68c628de948d1","source":"org.jhotdraw.draw","label":"contains","properties":{"weight":1,"metaSrc":"source code"},"target":"org.jhotdraw.draw.connector"}},{"data":{"id":"fdad0d36ca342e5801f970565a87beb9","source":"org.jhotdraw","label":"contains","properties":{"weight":1,"metaSrc":"source code"},"target":"org.jhotdraw.undo"}},{"data":{"id":"b46b034d6e7a7e7eb18ff4a7a37f3fff","source":"org.jhotdraw.samples.svg","label":"contains","properties":{"weight":1,"metaSrc":"source code"},"target":"org.jhotdraw.samples.svg.figures"}},{"data":{"id":"b18879dfdb66ae54d8cdbb0416666331","source":"org.jhotdraw.app","label":"contains","properties":{"weight":1,"metaSrc":"source code"},"target":"org.jhotdraw.app.action"}},{"data":{"id":"0b03959e3091e3e62f6df57fb946ed45","source":"org.jhotdraw.util","label":"contains","properties":{"weight":1,"metaSrc":"source code"},"target":"org.jhotdraw.util.prefs"}},{"data":{"id":"0199f13a33d60815fda7e1035787f642","source":"org.jhotdraw.draw","label":"contains","properties":{"weight":1,"metaSrc":"source code"},"target":"org.jhotdraw.draw.print"}},{"data":{"id":"01e72c2531bf7b1db4bc2513325c3a6c","source":"org.jhotdraw.app.action","label":"contains","properties":{"weight":1,"metaSrc":"source code"},"target":"org.jhotdraw.app.action.edit"}},{"data":{"id":"7053358fea2dac231da091de14444bb1","source":"org.jhotdraw.gui","label":"contains","properties":{"weight":1,"metaSrc":"source code"},"target":"org.jhotdraw.gui.filechooser"}},{"data":{"id":"c4c6a2e737296540e31068c40a23718b","source":"org.jhotdraw.samples","label":"contains","properties":{"weight":1,"metaSrc":"source code"},"target":"org.jhotdraw.samples.teddy"}},{"data":{"id":"a93130d849454762ec8930973e2544d1","source":"org.jhotdraw.gui.plaf.palette","label":"contains","properties":{"weight":1,"metaSrc":"source code"},"target":"org.jhotdraw.gui.plaf.palette.colorchooser"}},{"data":{"id":"49e97be81379d9c1cec04e3cf09e09ed","source":"org.jhotdraw.app.action","label":"contains","properties":{"weight":1,"metaSrc":"source code"},"target":"org.jhotdraw.app.action.view"}},{"data":{"id":"792769bbb9e9d88b66bffe6cb5465a68","source":"org.jhotdraw.samples.odg","label":"contains","properties":{"weight":1,"metaSrc":"source code"},"target":"org.jhotdraw.samples.odg.action"}},{"data":{"id":"b3a5ece19a7ce1547d12fe311bcbc189","source":"org.jhotdraw.samples","label":"contains","properties":{"weight":1,"metaSrc":"source code"},"target":"org.jhotdraw.samples.draw"}},{"data":{"id":"fbef7d486fd0a6d87785471b54628cb7","source":"org.jhotdraw","label":"contains","properties":{"weight":1,"metaSrc":"source code"},"target":"org.jhotdraw.app"}},{"data":{"id":"7bfeeb7ca89a77f55dc06cc6c40bc1d3","source":"org.jhotdraw","label":"contains","properties":{"weight":1,"metaSrc":"source code"},"target":"org.jhotdraw.io"}},{"data":{"id":"4ccf57be525c95994cbe1de9709f1642","source":"org.jhotdraw.draw","label":"contains","properties":{"weight":1,"metaSrc":"source code"},"target":"org.jhotdraw.draw.action"}},{"data":{"id":"c4206c4f1b45cdbe2dc27805f9664c95","source":"org.jhotdraw.gui","label":"contains","properties":{"weight":1,"metaSrc":"source code"},"target":"org.jhotdraw.gui.fontchooser"}},{"data":{"id":"d3040db50bf6d92edddc959daeba0a44","source":"org.jhotdraw.samples","label":"contains","properties":{"weight":1,"metaSrc":"source code"},"target":"org.jhotdraw.samples.mini"}},{"data":{"id":"6fbd7d0b1953ee6a5cb67c29c322d244","source":"org.jhotdraw","label":"contains","properties":{"weight":1,"metaSrc":"source code"},"target":"org.jhotdraw.samples"}},{"data":{"id":"5f15b85419ca3b470f90ca29cdf466cf","source":"org.jhotdraw","label":"contains","properties":{"weight":1,"metaSrc":"source code"},"target":"org.jhotdraw.util"}},{"data":{"id":"51504ef64b209597010c231587459bbb","source":"net.n3","label":"contains","properties":{"weight":1,"metaSrc":"source code"},"target":"net.n3.nanoxml"}},{"data":{"id":"f5415f131d39133722f884b7f0238379","source":"org.jhotdraw.samples.svg","label":"contains","properties":{"weight":1,"metaSrc":"source code"},"target":"org.jhotdraw.samples.svg.gui"}},{"data":{"id":"d11feff606f17f3afdad767b1754330b","source":"org.jhotdraw.draw","label":"contains","properties":{"weight":1,"metaSrc":"source code"},"target":"org.jhotdraw.draw.handle"}},{"data":{"id":"e573ccd7a82f9992f75855be800e6067","source":"org.jhotdraw.draw","label":"contains","properties":{"weight":1,"metaSrc":"source code"},"target":"org.jhotdraw.draw.io"}},{"data":{"id":"3cc311b380710b8fd21f91dd95a9130c","source":"org.jhotdraw.draw","label":"contains","properties":{"weight":1,"metaSrc":"source code"},"target":"org.jhotdraw.draw.decoration"}},{"data":{"id":"06c00d6418c71c31eabbc402045124ac","source":"org.jhotdraw.app.action","label":"contains","properties":{"weight":1,"metaSrc":"source code"},"target":"org.jhotdraw.app.action.file"}},{"data":{"id":"6c1837445ae5b8a93ae77ddd7237e333","source":"org.jhotdraw.samples.teddy","label":"contains","properties":{"weight":1,"metaSrc":"source code"},"target":"org.jhotdraw.samples.teddy.io"}},{"data":{"id":"19e14429460d1868746b63be18178cf3","source":"org.jhotdraw.samples","label":"contains","properties":{"weight":1,"metaSrc":"source code"},"target":"org.jhotdraw.samples.pert"}},{"data":{"id":"fcd1d3a1566b520612aa74a9fa211c52","source":"org.jhotdraw.draw","label":"contains","properties":{"weight":1,"metaSrc":"source code"},"target":"org.jhotdraw.draw.layouter"}},{"data":{"id":"1ac360770f75ffac9921909b853e2eef","source":"org.jhotdraw.draw","label":"contains","properties":{"weight":1,"metaSrc":"source code"},"target":"org.jhotdraw.draw.gui"}},{"data":{"id":"05d72c10e217636b706ae90b19da4ff3","source":"org.jhotdraw.samples","label":"contains","properties":{"weight":1,"metaSrc":"source code"},"target":"org.jhotdraw.samples.net"}},{"data":{"id":"eacfc7ff70e7b0d131ce25e1afad5f1d","source":"org.jhotdraw","label":"contains","properties":{"weight":1,"metaSrc":"source code"},"target":"org.jhotdraw.draw"}},{"data":{"id":"0d54dc762655fe81da02c3120d1ea225","source":"org.jhotdraw.samples.odg","label":"contains","properties":{"weight":1,"metaSrc":"source code"},"target":"org.jhotdraw.samples.odg.io"}},{"data":{"id":"616620cabaed8737e598a96ddaae10f1","source":"org.jhotdraw.samples","label":"contains","properties":{"weight":1,"metaSrc":"source code"},"target":"org.jhotdraw.samples.svg"}},{"data":{"id":"881f71db3a8ab8e1cddf4b8fac908e93","source":"org.jhotdraw.app.action","label":"contains","properties":{"weight":1,"metaSrc":"source code"},"target":"org.jhotdraw.app.action.app"}},{"data":{"id":"40891d9796e9e31461131c47ebb7e8f6","source":"org.jhotdraw","label":"contains","properties":{"weight":1,"metaSrc":"source code"},"target":"org.jhotdraw.net"}},{"data":{"id":"ec35228f47e0b8ab95fb906e3518f315","source":"org.jhotdraw.draw","label":"contains","properties":{"weight":1,"metaSrc":"source code"},"target":"org.jhotdraw.draw.liner"}},{"data":{"id":"cee3c56b07db1bf2dec7cbd779db1cbb","source":"org.jhotdraw.samples.teddy","label":"contains","properties":{"weight":1,"metaSrc":"source code"},"target":"org.jhotdraw.samples.teddy.action"}},{"data":{"id":"91771e06a5d23144558ea760167c1527","source":"org.jhotdraw.samples","label":"contains","properties":{"weight":1,"metaSrc":"source code"},"target":"org.jhotdraw.samples.color"}},{"data":{"id":"ba47d550e2f1d512c1e96b50c85d26e2","source":"org.jhotdraw","label":"contains","properties":{"weight":1,"metaSrc":"source code"},"target":"org.jhotdraw.text"}},{"data":{"id":"9be2547170ec4421a9b76dd48afd3294","source":"org.jhotdraw.gui.plaf","label":"contains","properties":{"weight":1,"metaSrc":"source code"},"target":"org.jhotdraw.gui.plaf.palette"}},{"data":{"id":"29d7f111d68b98fef85c2efa96e07543","source":"org.jhotdraw.samples.odg","label":"contains","properties":{"weight":1,"metaSrc":"source code"},"target":"org.jhotdraw.samples.odg.figures"}},{"data":{"id":"420e504078dcedbaa0c2f48c2865d93d","source":"org.jhotdraw.samples.pert","label":"contains","properties":{"weight":1,"metaSrc":"source code"},"target":"org.jhotdraw.samples.pert.figures"}},{"data":{"id":"f2f7bd313dfb43f29abe0df89c893af8","source":"org.jhotdraw.samples.teddy","label":"contains","properties":{"weight":1,"metaSrc":"source code"},"target":"org.jhotdraw.samples.teddy.regex"}},{"data":{"id":"9212845b2d749d3c3c96c33807441d04","source":"org.jhotdraw","label":"contains","properties":{"weight":1,"metaSrc":"source code"},"target":"org.jhotdraw.color"}},{"data":{"id":"3c10392b42fb169efce3be025dca371c","source":"org.jhotdraw.draw","label":"contains","properties":{"weight":1,"metaSrc":"source code"},"target":"org.jhotdraw.draw.locator"}},{"data":{"id":"cfcb1ac89d861cf4c32daa28b2652f8a","source":"org.jhotdraw","label":"contains","properties":{"weight":1,"metaSrc":"source code"},"target":"org.jhotdraw.beans"}},{"data":{"id":"38b851c45375b70411e19bf23cad443a","source":"net","label":"contains","properties":{"weight":1,"metaSrc":"source code"},"target":"net.n3"}},{"data":{"id":"0602120867c340ded72b1a3492f331a5","source":"org.jhotdraw.draw","label":"contains","properties":{"weight":1,"metaSrc":"source code"},"target":"org.jhotdraw.draw.tool"}},{"data":{"id":"9348f31118474bc974954417e7c65c9a","source":"org.jhotdraw.xml","label":"contains","properties":{"weight":1,"metaSrc":"source code"},"target":"org.jhotdraw.xml.css"}},{"data":{"id":"46c87081180a18ceaa78803e5b8ebbcc","source":"org","label":"contains","properties":{"weight":1,"metaSrc":"source code"},"target":"org.jhotdraw"}},{"data":{"id":"974892d15cb72b9c2236d2166dde081b","source":"org.jhotdraw.samples.net","label":"contains","properties":{"weight":1,"metaSrc":"source code"},"target":"org.jhotdraw.samples.net.figures"}},{"data":{"id":"97e31203fb95d905f87599848a283a33","source":"org.jhotdraw.samples.odg","label":"contains","properties":{"weight":1,"metaSrc":"source code"},"target":"org.jhotdraw.samples.odg.geom"}},{"data":{"id":"2762cb00b6499443bc23886fa374358d","source":"org.jhotdraw.samples.svg","label":"contains","properties":{"weight":1,"metaSrc":"source code"},"target":"org.jhotdraw.samples.svg.io"}},{"data":{"id":"d2eb5c84157d689af630ac36fb4756a7","source":"org.jhotdraw.draw","label":"contains","properties":{"weight":1,"metaSrc":"source code"},"target":"org.jhotdraw.draw.event"}},{"data":{"id":"d9bba03afd765d82e6182c40533df65d","source":"org.jhotdraw.samples.svg","label":"contains","properties":{"weight":1,"metaSrc":"source code"},"target":"org.jhotdraw.samples.svg.action"}},{"data":{"id":"d6455a17cb4877f0a9eec3af82a03917","source":"org.jhotdraw.draw","label":"contains","properties":{"weight":1,"metaSrc":"source code"},"target":"org.jhotdraw.draw.text"}},{"data":{"id":"da416cc6ef15910b1e09573d609f8fa8","source":"org.jhotdraw.samples.teddy","label":"contains","properties":{"weight":1,"metaSrc":"source code"},"target":"org.jhotdraw.samples.teddy.text"}},{"data":{"id":"c818927e9397fbaa67e22d283482dfed","source":"org.jhotdraw.samples","label":"contains","properties":{"weight":1,"metaSrc":"source code"},"target":"org.jhotdraw.samples.font"}},{"data":{"id":"1e930c75a503f166d36774b6aa2e4c16","source":"org.jhotdraw.gui","label":"contains","properties":{"weight":1,"metaSrc":"source code"},"target":"org.jhotdraw.gui.plaf"}},{"data":{"id":"2d62fb17476a51af635ef3f1d50c16cb","source":"org.jhotdraw.app.action","label":"contains","properties":{"weight":1,"metaSrc":"source code"},"target":"org.jhotdraw.app.action.window"}},{"data":{"id":"91d61157b1f428d935b18f712bffa534","source":"org.jhotdraw.samples","label":"contains","properties":{"weight":1,"metaSrc":"source code"},"target":"org.jhotdraw.samples.odg"}},{"data":{"id":"19f5f00541024e387eb052f7a47b526f","source":"org.jhotdraw","label":"contains","properties":{"weight":1,"metaSrc":"source code"},"target":"org.jhotdraw.geom"}},{"data":{"id":"c621a86b986155be1d7f747f5b7783e7","source":"org.jhotdraw.app","label":"contains","properties":{"weight":1,"metaSrc":"source code"},"target":"org.jhotdraw.app.osx"}},{"data":{"id":"5732fb5dfc8d959256133d466a958f5b","source":"org.jhotdraw","label":"contains","properties":{"weight":1,"metaSrc":"source code"},"target":"org.jhotdraw.gui"}},{"data":{"id":"1f798cf408ac21559dbf8c80c45b9dee","source":"org.jhotdraw","label":"contains","properties":{"weight":1,"metaSrc":"source code"},"target":"org.jhotdraw.xml"}},{"data":{"id":"f2a1c531e3421a92e48997b5476d7c2f","source":"org.jhotdraw.gui","label":"contains","properties":{"weight":1,"metaSrc":"source code"},"target":"org.jhotdraw.gui.datatransfer"}},{"data":{"id":"44350894fb4f7ea1c4e2ace081455b3c","source":"org.jhotdraw.gui","label":"contains","properties":{"weight":1,"metaSrc":"source code"},"target":"org.jhotdraw.gui.event"}},{"data":{"source":"org.jhotdraw.app.action.edit","target":"org.jhotdraw.util","label":"depends","properties":{"weight":5}}},{"data":{"source":"org.jhotdraw.samples.net","target":"org.jhotdraw.xml","label":"depends","properties":{"weight":1}}},{"data":{"source":"org.jhotdraw.draw.action","target":"org.jhotdraw.draw","label":"depends","properties":{"weight":32}}},{"data":{"source":"org.jhotdraw.app.action.window","target":"org.jhotdraw.gui","label":"depends","properties":{"weight":1}}},{"data":{"source":"org.jhotdraw.samples.odg","target":"org.jhotdraw.draw","label":"depends","properties":{"weight":4}}},{"data":{"source":"org.jhotdraw.draw.action","target":"org.jhotdraw.gui","label":"depends","properties":{"weight":1}}},{"data":{"source":"org.jhotdraw.samples.svg.figures","target":"org.jhotdraw.draw.handle","label":"depends","properties":{"weight":7}}},{"data":{"source":"org.jhotdraw.draw.io","target":"org.jhotdraw.draw","label":"depends","properties":{"weight":4}}},{"data":{"source":"org.jhotdraw.draw.handle","target":"org.jhotdraw.draw","label":"depends","properties":{"weight":38}}},{"data":{"source":"org.jhotdraw.samples.odg","target":"org.jhotdraw.draw.io","label":"depends","properties":{"weight":1}}},{"data":{"source":"org.jhotdraw.samples.mini","target":"org.jhotdraw.draw.io","label":"depends","properties":{"weight":1}}},{"data":{"source":"org.jhotdraw.gui.plaf.palette.colorchooser","target":"org.jhotdraw.color","label":"depends","properties":{"weight":10}}},{"data":{"source":"org.jhotdraw.draw.action","target":"org.jhotdraw.util","label":"depends","properties":{"weight":9}}},{"data":{"source":"org.jhotdraw.draw.connector","target":"org.jhotdraw.draw","label":"depends","properties":{"weight":4}}},{"data":{"source":"org.jhotdraw.undo","target":"org.jhotdraw.util","label":"depends","properties":{"weight":7}}},{"data":{"source":"org.jhotdraw.samples.svg.gui","target":"org.jhotdraw.util","label":"depends","properties":{"weight":3}}},{"data":{"source":"org.jhotdraw.samples.svg","target":"org.jhotdraw.draw","label":"depends","properties":{"weight":13}}},{"data":{"source":"org.jhotdraw.samples.svg.gui","target":"org.jhotdraw.gui.plaf.palette","label":"depends","properties":{"weight":17}}},{"data":{"source":"org.jhotdraw.samples.pert.figures","target":"org.jhotdraw.draw.event","label":"depends","properties":{"weight":2}}},{"data":{"source":"org.jhotdraw.draw","target":"org.jhotdraw.xml","label":"depends","properties":{"weight":11}}},{"data":{"source":"org.jhotdraw.draw.connector","target":"org.jhotdraw.xml","label":"depends","properties":{"weight":1}}},{"data":{"source":"org.jhotdraw.samples.pert","target":"org.jhotdraw.draw","label":"depends","properties":{"weight":2}}},{"data":{"source":"org.jhotdraw.samples.odg.action","target":"org.jhotdraw.util","label":"depends","properties":{"weight":1}}},{"data":{"source":"org.jhotdraw.draw","target":"org.jhotdraw.draw.layouter","label":"depends","properties":{"weight":2}}},{"data":{"source":"org.jhotdraw.app.action","target":"org.jhotdraw.app","label":"depends","properties":{"weight":7}}},{"data":{"source":"org.jhotdraw.samples.svg.figures","target":"org.jhotdraw.draw","label":"depends","properties":{"weight":8}}},{"data":{"source":"org.jhotdraw.app.action.file","target":"org.jhotdraw.app.action","label":"depends","properties":{"weight":2}}},{"data":{"source":"org.jhotdraw.samples.svg","target":"org.jhotdraw.app","label":"depends","properties":{"weight":3}}},{"data":{"source":"org.jhotdraw.text","target":"org.jhotdraw.util","label":"depends","properties":{"weight":6}}},{"data":{"source":"org.jhotdraw.samples.mini","target":"org.jhotdraw.draw","label":"depends","properties":{"weight":20}}},{"data":{"source":"org.jhotdraw.draw","target":"org.jhotdraw.draw.event","label":"depends","properties":{"weight":6}}},{"data":{"source":"org.jhotdraw.gui.plaf.palette.colorchooser","target":"org.jhotdraw.gui.plaf.palette","label":"depends","properties":{"weight":3}}},{"data":{"source":"org.jhotdraw.app.action.file","target":"org.jhotdraw.net","label":"depends","properties":{"weight":1}}},{"data":{"source":"org.jhotdraw.app","target":"org.jhotdraw.gui","label":"depends","properties":{"weight":1}}},{"data":{"source":"org.jhotdraw.app.action.file","target":"org.jhotdraw.util","label":"depends","properties":{"weight":5}}},{"data":{"source":"org.jhotdraw.app.action.app","target":"org.jhotdraw.app","label":"depends","properties":{"weight":1}}},{"data":{"source":"org.jhotdraw.gui","target":"org.jhotdraw.gui.event","label":"depends","properties":{"weight":3}}},{"data":{"source":"org.jhotdraw.draw.decoration","target":"org.jhotdraw.xml","label":"depends","properties":{"weight":1}}},{"data":{"source":"org.jhotdraw.samples.odg.action","target":"org.jhotdraw.draw","label":"depends","properties":{"weight":1}}},{"data":{"source":"org.jhotdraw.draw.event","target":"org.jhotdraw.draw","label":"depends","properties":{"weight":17}}},{"data":{"source":"org.jhotdraw.samples.mini","target":"org.jhotdraw.draw.action","label":"depends","properties":{"weight":1}}},{"data":{"source":"org.jhotdraw.samples.svg.gui","target":"org.jhotdraw.draw","label":"depends","properties":{"weight":6}}},{"data":{"source":"org.jhotdraw.samples.svg.io","target":"org.jhotdraw.draw","label":"depends","properties":{"weight":2}}},{"data":{"source":"org.jhotdraw.draw.tool","target":"org.jhotdraw.draw","label":"depends","properties":{"weight":11}}},{"data":{"source":"org.jhotdraw.samples.color","target":"org.jhotdraw.color","label":"depends","properties":{"weight":4}}},{"data":{"source":"org.jhotdraw.samples.draw","target":"org.jhotdraw.undo","label":"depends","properties":{"weight":1}}},{"data":{"source":"org.jhotdraw.app.action.app","target":"org.jhotdraw.app.action","label":"depends","properties":{"weight":4}}},{"data":{"source":"org.jhotdraw.draw.liner","target":"org.jhotdraw.draw","label":"depends","properties":{"weight":2}}},{"data":{"source":"org.jhotdraw.samples.odg.figures","target":"org.jhotdraw.samples.odg","label":"depends","properties":{"weight":1}}},{"data":{"source":"org.jhotdraw.draw.layouter","target":"org.jhotdraw.draw","label":"depends","properties":{"weight":4}}},{"data":{"source":"org.jhotdraw.samples.svg.figures","target":"org.jhotdraw.util","label":"depends","properties":{"weight":2}}},{"data":{"source":"org.jhotdraw.draw.locator","target":"org.jhotdraw.draw","label":"depends","properties":{"weight":4}}},{"data":{"source":"org.jhotdraw.samples.odg.figures","target":"org.jhotdraw.geom","label":"depends","properties":{"weight":2}}},{"data":{"source":"org.jhotdraw.gui.plaf.palette","target":"org.jhotdraw.gui.plaf.palette.colorchooser","label":"depends","properties":{"weight":5}}},{"data":{"source":"org.jhotdraw.samples.net","target":"org.jhotdraw.draw","label":"depends","properties":{"weight":4}}},{"data":{"source":"org.jhotdraw.samples.net.figures","target":"org.jhotdraw.draw","label":"depends","properties":{"weight":1}}},{"data":{"source":"org.jhotdraw.draw.gui","target":"org.jhotdraw.gui","label":"depends","properties":{"weight":3}}},{"data":{"source":"org.jhotdraw.samples.svg.gui","target":"org.jhotdraw.draw.event","label":"depends","properties":{"weight":1}}},{"data":{"source":"org.jhotdraw.draw","target":"org.jhotdraw.beans","label":"depends","properties":{"weight":4}}},{"data":{"source":"org.jhotdraw.gui.plaf.palette","target":"org.jhotdraw.util","label":"depends","properties":{"weight":5}}},{"data":{"source":"org.jhotdraw.samples.svg.gui","target":"org.jhotdraw.gui","label":"depends","properties":{"weight":5}}},{"data":{"source":"org.jhotdraw.samples.draw","target":"org.jhotdraw.draw","label":"depends","properties":{"weight":2}}},{"data":{"source":"org.jhotdraw.draw.event","target":"org.jhotdraw.draw.handle","label":"depends","properties":{"weight":5}}},{"data":{"source":"org.jhotdraw.samples.odg","target":"org.jhotdraw.app","label":"depends","properties":{"weight":1}}},{"data":{"source":"org.jhotdraw.samples.draw","target":"org.jhotdraw.app","label":"depends","properties":{"weight":1}}},{"data":{"source":"org.jhotdraw.app.action.edit","target":"org.jhotdraw.gui","label":"depends","properties":{"weight":2}}},{"data":{"source":"org.jhotdraw.draw.event","target":"org.jhotdraw.util","label":"depends","properties":{"weight":1}}},{"data":{"source":"org.jhotdraw.samples.svg.gui","target":"org.jhotdraw.text","label":"depends","properties":{"weight":3}}},{"data":{"source":"org.jhotdraw.samples.odg.figures","target":"org.jhotdraw.draw","label":"depends","properties":{"weight":5}}},{"data":{"source":"org.jhotdraw.samples.pert","target":"org.jhotdraw.xml","label":"depends","properties":{"weight":2}}},{"data":{"source":"org.jhotdraw.draw.decoration","target":"org.jhotdraw.draw","label":"depends","properties":{"weight":1}}},{"data":{"source":"org.jhotdraw.draw.handle","target":"org.jhotdraw.draw.event","label":"depends","properties":{"weight":3}}},{"data":{"source":"org.jhotdraw.samples.svg.action","target":"org.jhotdraw.util","label":"depends","properties":{"weight":1}}},{"data":{"source":"org.jhotdraw.app.action.app","target":"org.jhotdraw.app.action.file","label":"depends","properties":{"weight":2}}},{"data":{"source":"org.jhotdraw.samples.teddy","target":"org.jhotdraw.app","label":"depends","properties":{"weight":1}}},{"data":{"source":"org.jhotdraw.app.action.view","target":"org.jhotdraw.app.action","label":"depends","properties":{"weight":5}}},{"data":{"source":"org.jhotdraw.samples.teddy","target":"org.jhotdraw.app.action","label":"depends","properties":{"weight":3}}},{"data":{"source":"org.jhotdraw.samples.svg.io","target":"org.jhotdraw.samples.svg.figures","label":"depends","properties":{"weight":2}}},{"data":{"source":"org.jhotdraw.draw.io","target":"org.jhotdraw.xml","label":"depends","properties":{"weight":3}}},{"data":{"source":"org.jhotdraw.samples.svg","target":"org.jhotdraw.samples.svg.gui","label":"depends","properties":{"weight":11}}},{"data":{"source":"org.jhotdraw.samples.mini","target":"org.jhotdraw.geom","label":"depends","properties":{"weight":1}}},{"data":{"source":"org.jhotdraw.draw.liner","target":"org.jhotdraw.geom","label":"depends","properties":{"weight":1}}},{"data":{"source":"org.jhotdraw.app.action.window","target":"org.jhotdraw.app.action","label":"depends","properties":{"weight":1}}},{"data":{"source":"org.jhotdraw.samples.pert","target":"org.jhotdraw.app","label":"depends","properties":{"weight":1}}},{"data":{"source":"org.jhotdraw.samples.teddy.action","target":"org.jhotdraw.samples.teddy","label":"depends","properties":{"weight":3}}},{"data":{"source":"org.jhotdraw.draw.tool","target":"org.jhotdraw.draw.text","label":"depends","properties":{"weight":2}}},{"data":{"source":"org.jhotdraw.draw","target":"org.jhotdraw.geom","label":"depends","properties":{"weight":16}}},{"data":{"source":"org.jhotdraw.samples.svg.gui","target":"org.jhotdraw.undo","label":"depends","properties":{"weight":1}}},{"data":{"source":"org.jhotdraw.samples.odg","target":"org.jhotdraw.text","label":"depends","properties":{"weight":1}}},{"data":{"source":"org.jhotdraw.draw.handle","target":"org.jhotdraw.geom","label":"depends","properties":{"weight":1}}},{"data":{"source":"org.jhotdraw.app.action.window","target":"org.jhotdraw.app","label":"depends","properties":{"weight":2}}},{"data":{"source":"org.jhotdraw.samples.teddy.action","target":"org.jhotdraw.app.action.edit","label":"depends","properties":{"weight":1}}},{"data":{"source":"org.jhotdraw.draw.handle","target":"org.jhotdraw.util","label":"depends","properties":{"weight":1}}},{"data":{"source":"org.jhotdraw.samples.svg.action","target":"org.jhotdraw.draw.action","label":"depends","properties":{"weight":2}}},{"data":{"source":"org.jhotdraw.samples.draw","target":"org.jhotdraw.xml","label":"depends","properties":{"weight":1}}},{"data":{"source":"org.jhotdraw.samples.pert","target":"org.jhotdraw.draw.action","label":"depends","properties":{"weight":1}}},{"data":{"source":"org.jhotdraw.draw.handle","target":"org.jhotdraw.draw.locator","label":"depends","properties":{"weight":1}}},{"data":{"source":"org.jhotdraw.app.action.file","target":"org.jhotdraw.app","label":"depends","properties":{"weight":3}}},{"data":{"source":"org.jhotdraw.color","target":"org.jhotdraw.beans","label":"depends","properties":{"weight":1}}},{"data":{"source":"org.jhotdraw.draw.connector","target":"org.jhotdraw.geom","label":"depends","properties":{"weight":1}}},{"data":{"source":"org.jhotdraw.draw","target":"org.jhotdraw.draw.handle","label":"depends","properties":{"weight":2}}},{"data":{"source":"org.jhotdraw.draw.layouter","target":"org.jhotdraw.geom","label":"depends","properties":{"weight":1}}},{"data":{"source":"org.jhotdraw.samples.odg.io","target":"net.n3.nanoxml","label":"depends","properties":{"weight":11}}},{"data":{"source":"org.jhotdraw.samples.mini","target":"org.jhotdraw.util","label":"depends","properties":{"weight":1}}},{"data":{"source":"org.jhotdraw.samples.svg","target":"org.jhotdraw.draw.tool","label":"depends","properties":{"weight":1}}},{"data":{"source":"org.jhotdraw.draw","target":"org.jhotdraw.util","label":"depends","properties":{"weight":1}}},{"data":{"source":"org.jhotdraw.draw.gui","target":"org.jhotdraw.util","label":"depends","properties":{"weight":1}}},{"data":{"source":"org.jhotdraw.app.action.view","target":"org.jhotdraw.app","label":"depends","properties":{"weight":1}}},{"data":{"source":"org.jhotdraw.draw.print","target":"org.jhotdraw.draw","label":"depends","properties":{"weight":1}}},{"data":{"source":"org.jhotdraw.draw.locator","target":"org.jhotdraw.xml","label":"depends","properties":{"weight":2}}},{"data":{"source":"org.jhotdraw.samples.odg.figures","target":"org.jhotdraw.draw.handle","label":"depends","properties":{"weight":2}}},{"data":{"source":"org.jhotdraw.xml","target":"net.n3.nanoxml","label":"depends","properties":{"weight":1}}},{"data":{"source":"org.jhotdraw.samples.pert.figures","target":"org.jhotdraw.draw","label":"depends","properties":{"weight":6}}},{"data":{"source":"org.jhotdraw.app.action.edit","target":"org.jhotdraw.gui.datatransfer","label":"depends","properties":{"weight":1}}},{"data":{"source":"org.jhotdraw.samples.draw","target":"org.jhotdraw.draw.action","label":"depends","properties":{"weight":1}}},{"data":{"source":"org.jhotdraw.samples.odg","target":"org.jhotdraw.undo","label":"depends","properties":{"weight":1}}},{"data":{"source":"org.jhotdraw.draw.text","target":"org.jhotdraw.draw","label":"depends","properties":{"weight":2}}},{"data":{"source":"org.jhotdraw.gui.datatransfer","target":"org.jhotdraw.util","label":"depends","properties":{"weight":1}}},{"data":{"source":"org.jhotdraw.samples.mini","target":"org.jhotdraw.xml","label":"depends","properties":{"weight":1}}},{"data":{"source":"org.jhotdraw.app","target":"org.jhotdraw.app.action","label":"depends","properties":{"weight":1}}},{"data":{"source":"org.jhotdraw.text","target":"org.jhotdraw.util.prefs","label":"depends","properties":{"weight":1}}},{"data":{"source":"org.jhotdraw.samples.net","target":"org.jhotdraw.app","label":"depends","properties":{"weight":1}}}]}}