{"elements":{"nodes":[{"data":{"id":"com.fsck.k9.ui.compose","properties":{"simpleName":"compose","kind":"package","metaSrc":"source code"},"labels":["Container"]}},{"data":{"id":"com.fsck.k9","properties":{"simpleName":"k9","kind":"package","metaSrc":"source code"},"labels":["Container"]}},{"data":{"id":"com.fsck.k9.mailstore.util","properties":{"simpleName":"util","kind":"package","metaSrc":"source code"},"labels":["Container"]}},{"data":{"id":"com.fsck.k9.controller","properties":{"simpleName":"controller","kind":"package","metaSrc":"source code"},"labels":["Container"]}},{"data":{"id":"com.fsck.k9.activity.compose","properties":{"simpleName":"compose","kind":"package","metaSrc":"source code"},"labels":["Container"]}},{"data":{"id":"com.fsck.k9.message.html","properties":{"simpleName":"html","kind":"package","metaSrc":"source code"},"labels":["Container"]}},{"data":{"id":"com.fsck.k9.activity.misc","properties":{"simpleName":"misc","kind":"package","metaSrc":"source code"},"labels":["Container"]}},{"data":{"id":"com.fsck.k9.ui","properties":{"simpleName":"ui","kind":"package","metaSrc":"source code"},"labels":["Container"]}},{"data":{"id":"com.fsck.k9.account","properties":{"simpleName":"account","kind":"package","metaSrc":"source code"},"labels":["Container"]}},{"data":{"id":"com.fsck","properties":{"simpleName":"fsck","kind":"package","metaSrc":"source code"},"labels":["Container"]}},{"data":{"id":"com.fsck.k9.activity.loader","properties":{"simpleName":"loader","kind":"package","metaSrc":"source code"},"labels":["Container"]}},{"data":{"id":"com.fsck.k9.setup","properties":{"simpleName":"setup","kind":"package","metaSrc":"source code"},"labels":["Container"]}},{"data":{"id":"com.fsck.k9.crypto","properties":{"simpleName":"crypto","kind":"package","metaSrc":"source code"},"labels":["Container"]}},{"data":{"id":"com.fsck.k9.message.extractors","properties":{"simpleName":"extractors","kind":"package","metaSrc":"source code"},"labels":["Container"]}},{"data":{"id":"com.fsck.k9.power","properties":{"simpleName":"power","kind":"package","metaSrc":"source code"},"labels":["Container"]}},{"data":{"id":"com.fsck.k9.notification","properties":{"simpleName":"notification","kind":"package","metaSrc":"source code"},"labels":["Container"]}},{"data":{"id":"com.fsck.k9.message.quote","properties":{"simpleName":"quote","kind":"package","metaSrc":"source code"},"labels":["Container"]}},{"data":{"id":"com.fsck.k9.ui.messageview","properties":{"simpleName":"messageview","kind":"package","metaSrc":"source code"},"labels":["Container"]}},{"data":{"id":"com.fsck.k9.autocrypt","properties":{"simpleName":"autocrypt","kind":"package","metaSrc":"source code"},"labels":["Container"]}},{"data":{"id":"com.fsck.k9.activity","properties":{"simpleName":"activity","kind":"package","metaSrc":"source code"},"labels":["Container"]}},{"data":{"id":"com.fsck.k9.cache","properties":{"simpleName":"cache","kind":"package","metaSrc":"source code"},"labels":["Container"]}},{"data":{"id":"com.fsck.k9.ui.message","properties":{"simpleName":"message","kind":"package","metaSrc":"source code"},"labels":["Container"]}},{"data":{"id":"com","properties":{"simpleName":"com","kind":"package","metaSrc":"source code"},"labels":["Container"]}},{"data":{"id":"com.fsck.k9.view","properties":{"simpleName":"view","kind":"package","metaSrc":"source code"},"labels":["Container"]}},{"data":{"id":"com.fsck.k9.message","properties":{"simpleName":"message","kind":"package","metaSrc":"source code"},"labels":["Container"]}},{"data":{"id":"com.fsck.k9.provider","properties":{"simpleName":"provider","kind":"package","metaSrc":"source code"},"labels":["Container"]}},{"data":{"id":"com.fsck.k9.fragment","properties":{"simpleName":"fragment","kind":"package","metaSrc":"source code"},"labels":["Container"]}},{"data":{"id":"com.fsck.k9.mailstore","properties":{"simpleName":"mailstore","kind":"package","metaSrc":"source code"},"labels":["Container"]}},{"data":{"id":"com.fsck.k9.activity.setup","properties":{"simpleName":"setup","kind":"package","metaSrc":"source code"},"labels":["Container"]}},{"data":{"id":"com.fsck.k9.message.signature","properties":{"simpleName":"signature","kind":"package","metaSrc":"source code"},"labels":["Container"]}},{"data":{"id":"com.fsck.k9.search","properties":{"simpleName":"search","kind":"package","metaSrc":"source code"},"labels":["Container"]}},{"data":{"id":"com.fsck.k9.remotecontrol","properties":{"simpleName":"remotecontrol","kind":"package","metaSrc":"source code"},"labels":["Container"]}},{"data":{"id":"com.fsck.k9.widget","properties":{"simpleName":"widget","kind":"package","metaSrc":"source code"},"labels":["Container"]}},{"data":{"id":"com.fsck.k9.mailstore.migrations","properties":{"simpleName":"migrations","kind":"package","metaSrc":"source code"},"labels":["Container"]}},{"data":{"id":"com.fsck.k9.helper.jsoup","properties":{"simpleName":"jsoup","kind":"package","metaSrc":"source code"},"labels":["Container"]}},{"data":{"id":"com.fsck.k9.service","properties":{"simpleName":"service","kind":"package","metaSrc":"source code"},"labels":["Container"]}},{"data":{"id":"com.fsck.k9.preferences","properties":{"simpleName":"preferences","kind":"package","metaSrc":"source code"},"labels":["Container"]}},{"data":{"id":"com.fsck.k9.ui.dialog","properties":{"simpleName":"dialog","kind":"package","metaSrc":"source code"},"labels":["Container"]}},{"data":{"id":"com.fsck.k9.ui.crypto","properties":{"simpleName":"crypto","kind":"package","metaSrc":"source code"},"labels":["Container"]}},{"data":{"id":"com.fsck.k9.helper","properties":{"simpleName":"helper","kind":"package","metaSrc":"source code"},"labels":["Container"]}},{"data":{"id":"com.fsck.k9.widget.list","properties":{"simpleName":"list","kind":"package","metaSrc":"source code"},"labels":["Container"]}}],"edges":[{"data":{"id":"205549359078d0bdd1b8c38ad76aa98d","source":"com.fsck.k9","label":"contains","properties":{"weight":1,"metaSrc":"source code"},"target":"com.fsck.k9.message"}},{"data":{"id":"d3c405e6527dfaa75148a4b5c936dc5b","source":"com.fsck.k9.helper","label":"contains","properties":{"weight":1,"metaSrc":"source code"},"target":"com.fsck.k9.helper.jsoup"}},{"data":{"id":"6c6b12a50ada3c230e425ddc5685ce27","source":"com.fsck.k9","label":"contains","properties":{"weight":1,"metaSrc":"source code"},"target":"com.fsck.k9.power"}},{"data":{"id":"f28e711956eb7c3b04b300ef5c294a48","source":"com.fsck.k9.message","label":"contains","properties":{"weight":1,"metaSrc":"source code"},"target":"com.fsck.k9.message.extractors"}},{"data":{"id":"c83a25607e7ffa307d7200c8c946c2a5","source":"com.fsck.k9","label":"contains","properties":{"weight":1,"metaSrc":"source code"},"target":"com.fsck.k9.provider"}},{"data":{"id":"13465b03eb3e67e90b739eaeb0f59d6f","source":"com.fsck.k9","label":"contains","properties":{"weight":1,"metaSrc":"source code"},"target":"com.fsck.k9.mailstore"}},{"data":{"id":"c1e829be12704a09a8b51bf0f3348f54","source":"com.fsck.k9","label":"contains","properties":{"weight":1,"metaSrc":"source code"},"target":"com.fsck.k9.ui"}},{"data":{"id":"bbbaa097888e97603f9762af57f7cab4","source":"com.fsck.k9","label":"contains","properties":{"weight":1,"metaSrc":"source code"},"target":"com.fsck.k9.search"}},{"data":{"id":"1411b6be6a436feb36830bcc7918119a","source":"com.fsck.k9","label":"contains","properties":{"weight":1,"metaSrc":"source code"},"target":"com.fsck.k9.controller"}},{"data":{"id":"4d201f8eeb2aea676494a0db5cd30563","source":"com.fsck.k9.ui","label":"contains","properties":{"weight":1,"metaSrc":"source code"},"target":"com.fsck.k9.ui.message"}},{"data":{"id":"df16685e898fed57c3fc5e22f6559896","source":"com.fsck.k9.ui","label":"contains","properties":{"weight":1,"metaSrc":"source code"},"target":"com.fsck.k9.ui.dialog"}},{"data":{"id":"67430d188f7e88a64af892562c332ca6","source":"com.fsck.k9.activity","label":"contains","properties":{"weight":1,"metaSrc":"source code"},"target":"com.fsck.k9.activity.compose"}},{"data":{"id":"be210c9be2492f2b44e00694367924bb","source":"com.fsck.k9.message","label":"contains","properties":{"weight":1,"metaSrc":"source code"},"target":"com.fsck.k9.message.signature"}},{"data":{"id":"e14932d4392c202aa54d40f09a51c1dd","source":"com.fsck.k9","label":"contains","properties":{"weight":1,"metaSrc":"source code"},"target":"com.fsck.k9.autocrypt"}},{"data":{"id":"50ab0cb0a6e6a0e6a867a2759238f794","source":"com.fsck.k9.message","label":"contains","properties":{"weight":1,"metaSrc":"source code"},"target":"com.fsck.k9.message.quote"}},{"data":{"id":"7ae45a34f582f440725b4547d8104bb4","source":"com.fsck.k9.ui","label":"contains","properties":{"weight":1,"metaSrc":"source code"},"target":"com.fsck.k9.ui.messageview"}},{"data":{"id":"28aa8d44c37ff3a8aa3c3eb3c4591c8b","source":"com.fsck.k9.activity","label":"contains","properties":{"weight":1,"metaSrc":"source code"},"target":"com.fsck.k9.activity.misc"}},{"data":{"id":"dbe78ea5b3c08f5f25b0855cea922ab2","source":"com.fsck.k9.mailstore","label":"contains","properties":{"weight":1,"metaSrc":"source code"},"target":"com.fsck.k9.mailstore.migrations"}},{"data":{"id":"d5f686a2e106df197f79f0dfe3322bfb","source":"com.fsck.k9","label":"contains","properties":{"weight":1,"metaSrc":"source code"},"target":"com.fsck.k9.notification"}},{"data":{"id":"1ad896a03f96e50013f6fbee9f7a6617","source":"com.fsck.k9","label":"contains","properties":{"weight":1,"metaSrc":"source code"},"target":"com.fsck.k9.widget"}},{"data":{"id":"44048f724c8615528b5040fa881a3062","source":"com.fsck.k9","label":"contains","properties":{"weight":1,"metaSrc":"source code"},"target":"com.fsck.k9.account"}},{"data":{"id":"eb139fa959da3df7a36992bfd3b66fdf","source":"com.fsck.k9","label":"contains","properties":{"weight":1,"metaSrc":"source code"},"target":"com.fsck.k9.fragment"}},{"data":{"id":"c6f1ea39a697950523843103c030f673","source":"com.fsck.k9","label":"contains","properties":{"weight":1,"metaSrc":"source code"},"target":"com.fsck.k9.helper"}},{"data":{"id":"42cb11902011598181334e66f471c5c7","source":"com.fsck.k9","label":"contains","properties":{"weight":1,"metaSrc":"source code"},"target":"com.fsck.k9.service"}},{"data":{"id":"88d20c9e7cf2522e89ae64cea0d6ece2","source":"com","label":"contains","properties":{"weight":1,"metaSrc":"source code"},"target":"com.fsck"}},{"data":{"id":"c38ae61a7bc9b72b0fe903e1ec9715d5","source":"com.fsck.k9.message","label":"contains","properties":{"weight":1,"metaSrc":"source code"},"target":"com.fsck.k9.message.html"}},{"data":{"id":"dcc5d2bcb41f6bdcbd0b664ac118241d","source":"com.fsck.k9.ui","label":"contains","properties":{"weight":1,"metaSrc":"source code"},"target":"com.fsck.k9.ui.compose"}},{"data":{"id":"37d75b79b5c96f390b85d2661d86e2b2","source":"com.fsck.k9.activity","label":"contains","properties":{"weight":1,"metaSrc":"source code"},"target":"com.fsck.k9.activity.setup"}},{"data":{"id":"27282cbd6fe4bc046278ba938dd29cae","source":"com.fsck.k9","label":"contains","properties":{"weight":1,"metaSrc":"source code"},"target":"com.fsck.k9.activity"}},{"data":{"id":"ca3c61181e9e891a84781454e38095d7","source":"com.fsck.k9","label":"contains","properties":{"weight":1,"metaSrc":"source code"},"target":"com.fsck.k9.preferences"}},{"data":{"id":"cdbf2078612d08e38c0500900cd28702","source":"com.fsck.k9","label":"contains","properties":{"weight":1,"metaSrc":"source code"},"target":"com.fsck.k9.view"}},{"data":{"id":"392b57e0bb3f618b33f7dd744794e7e3","source":"com.fsck.k9","label":"contains","properties":{"weight":1,"metaSrc":"source code"},"target":"com.fsck.k9.crypto"}},{"data":{"id":"36a28b1ffbd3efe61d67b9e262692d00","source":"com.fsck.k9","label":"contains","properties":{"weight":1,"metaSrc":"source code"},"target":"com.fsck.k9.cache"}},{"data":{"id":"8f40a719b1f5fb53c3d89522ea54fb27","source":"com.fsck","label":"contains","properties":{"weight":1,"metaSrc":"source code"},"target":"com.fsck.k9"}},{"data":{"id":"528c5882aaccc337f716d896c6355754","source":"com.fsck.k9","label":"contains","properties":{"weight":1,"metaSrc":"source code"},"target":"com.fsck.k9.remotecontrol"}},{"data":{"id":"94924281b562bf8d9c73b01a3a7e05e5","source":"com.fsck.k9.widget","label":"contains","properties":{"weight":1,"metaSrc":"source code"},"target":"com.fsck.k9.widget.list"}},{"data":{"id":"f240dcbe6f73f4da00cd97d95599961e","source":"com.fsck.k9","label":"contains","properties":{"weight":1,"metaSrc":"source code"},"target":"com.fsck.k9.setup"}},{"data":{"id":"c24f4ed89195446f8971cbd58efa97ac","source":"com.fsck.k9.activity","label":"contains","properties":{"weight":1,"metaSrc":"source code"},"target":"com.fsck.k9.activity.loader"}},{"data":{"id":"e670464c19eb8d9ed94e671449430e08","source":"com.fsck.k9.mailstore","label":"contains","properties":{"weight":1,"metaSrc":"source code"},"target":"com.fsck.k9.mailstore.util"}},{"data":{"id":"78d3a8db64af79a36e6739bd32abdad5","source":"com.fsck.k9.ui","label":"contains","properties":{"weight":1,"metaSrc":"source code"},"target":"com.fsck.k9.ui.crypto"}},{"data":{"source":"com.fsck.k9.provider","target":"com.fsck.k9.helper","label":"depends","properties":{"weight":2}}},{"data":{"source":"com.fsck.k9.ui.crypto","target":"com.fsck.k9.mailstore","label":"depends","properties":{"weight":1}}},{"data":{"source":"com.fsck.k9.crypto","target":"com.fsck.k9.ui.crypto","label":"depends","properties":{"weight":1}}},{"data":{"source":"com.fsck.k9.fragment","target":"com.fsck.k9.search","label":"depends","properties":{"weight":1}}},{"data":{"source":"com.fsck.k9.helper","target":"com.fsck.k9","label":"depends","properties":{"weight":7}}},{"data":{"source":"com.fsck.k9.activity","target":"com.fsck.k9.controller","label":"depends","properties":{"weight":2}}},{"data":{"source":"com.fsck.k9.activity.setup","target":"com.fsck.k9.helper","label":"depends","properties":{"weight":1}}},{"data":{"source":"com.fsck.k9.provider","target":"com.fsck.k9.mailstore","label":"depends","properties":{"weight":7}}},{"data":{"source":"com.fsck.k9.notification","target":"com.fsck.k9","label":"depends","properties":{"weight":4}}},{"data":{"source":"com.fsck.k9.mailstore","target":"com.fsck.k9.mailstore.util","label":"depends","properties":{"weight":2}}},{"data":{"source":"com.fsck.k9.preferences","target":"com.fsck.k9.helper","label":"depends","properties":{"weight":2}}},{"data":{"source":"com.fsck.k9.ui.messageview","target":"com.fsck.k9.helper","label":"depends","properties":{"weight":2}}},{"data":{"source":"com.fsck.k9.message.signature","target":"com.fsck.k9.helper.jsoup","label":"depends","properties":{"weight":1}}},{"data":{"source":"com.fsck.k9.cache","target":"com.fsck.k9.helper","label":"depends","properties":{"weight":1}}},{"data":{"source":"com.fsck.k9.message.extractors","target":"com.fsck.k9.crypto","label":"depends","properties":{"weight":1}}},{"data":{"source":"com.fsck.k9.activity","target":"com.fsck.k9.mailstore","label":"depends","properties":{"weight":3}}},{"data":{"source":"com.fsck.k9.cache","target":"com.fsck.k9.mailstore","label":"depends","properties":{"weight":1}}},{"data":{"source":"com.fsck.k9.message","target":"com.fsck.k9","label":"depends","properties":{"weight":1}}},{"data":{"source":"com.fsck.k9.activity","target":"com.fsck.k9","label":"depends","properties":{"weight":17}}},{"data":{"source":"com.fsck.k9.activity.compose","target":"com.fsck.k9.message","label":"depends","properties":{"weight":1}}},{"data":{"source":"com.fsck.k9.activity","target":"com.fsck.k9.helper","label":"depends","properties":{"weight":1}}},{"data":{"source":"com.fsck.k9.activity","target":"com.fsck.k9.activity.setup","label":"depends","properties":{"weight":2}}},{"data":{"source":"com.fsck.k9.preferences","target":"com.fsck.k9","label":"depends","properties":{"weight":1}}},{"data":{"source":"com.fsck.k9.activity","target":"com.fsck.k9.activity.misc","label":"depends","properties":{"weight":4}}},{"data":{"source":"com.fsck.k9.message.quote","target":"com.fsck.k9.message.html","label":"depends","properties":{"weight":6}}},{"data":{"source":"com.fsck.k9.activity.loader","target":"com.fsck.k9.activity.misc","label":"depends","properties":{"weight":2}}},{"data":{"source":"com.fsck.k9.mailstore","target":"com.fsck.k9.message.extractors","label":"depends","properties":{"weight":1}}},{"data":{"source":"com.fsck.k9.service","target":"com.fsck.k9.mailstore","label":"depends","properties":{"weight":3}}},{"data":{"source":"com.fsck.k9.message","target":"com.fsck.k9.crypto","label":"depends","properties":{"weight":2}}},{"data":{"source":"com.fsck.k9.ui.compose","target":"com.fsck.k9.view","label":"depends","properties":{"weight":1}}},{"data":{"source":"com.fsck.k9.activity.compose","target":"com.fsck.k9.controller","label":"depends","properties":{"weight":1}}},{"data":{"source":"com.fsck.k9.helper","target":"com.fsck.k9.search","label":"depends","properties":{"weight":1}}},{"data":{"source":"com.fsck.k9.activity.compose","target":"com.fsck.k9.view","label":"depends","properties":{"weight":4}}},{"data":{"source":"com.fsck.k9.activity.setup","target":"com.fsck.k9","label":"depends","properties":{"weight":5}}},{"data":{"source":"com.fsck.k9.provider","target":"com.fsck.k9","label":"depends","properties":{"weight":2}}},{"data":{"source":"com.fsck.k9.fragment","target":"com.fsck.k9","label":"depends","properties":{"weight":1}}},{"data":{"source":"com.fsck.k9","target":"com.fsck.k9.power","label":"depends","properties":{"weight":1}}},{"data":{"source":"com.fsck.k9.service","target":"com.fsck.k9.controller","label":"depends","properties":{"weight":1}}},{"data":{"source":"com.fsck.k9.mailstore.migrations","target":"com.fsck.k9.mailstore","label":"depends","properties":{"weight":2}}},{"data":{"source":"com.fsck.k9.activity.setup","target":"com.fsck.k9.activity","label":"depends","properties":{"weight":4}}},{"data":{"source":"com.fsck.k9.ui.compose","target":"com.fsck.k9.message.signature","label":"depends","properties":{"weight":1}}},{"data":{"source":"com.fsck.k9.notification","target":"com.fsck.k9.helper","label":"depends","properties":{"weight":1}}},{"data":{"source":"com.fsck.k9.crypto","target":"com.fsck.k9","label":"depends","properties":{"weight":1}}},{"data":{"source":"com.fsck.k9","target":"com.fsck.k9.mailstore","label":"depends","properties":{"weight":1}}},{"data":{"source":"com.fsck.k9.message.extractors","target":"com.fsck.k9.message.html","label":"depends","properties":{"weight":2}}},{"data":{"source":"com.fsck.k9.helper","target":"com.fsck.k9.ui","label":"depends","properties":{"weight":1}}},{"data":{"source":"com.fsck.k9.view","target":"com.fsck.k9.mailstore","label":"depends","properties":{"weight":2}}},{"data":{"source":"com.fsck.k9.activity.compose","target":"com.fsck.k9","label":"depends","properties":{"weight":2}}},{"data":{"source":"com.fsck.k9.ui.messageview","target":"com.fsck.k9","label":"depends","properties":{"weight":1}}},{"data":{"source":"com.fsck.k9.activity.setup","target":"com.fsck.k9.controller","label":"depends","properties":{"weight":1}}},{"data":{"source":"com.fsck.k9.notification","target":"com.fsck.k9.controller","label":"depends","properties":{"weight":1}}},{"data":{"source":"com.fsck.k9.activity","target":"com.fsck.k9.ui","label":"depends","properties":{"weight":1}}},{"data":{"source":"com.fsck.k9.message.quote","target":"com.fsck.k9","label":"depends","properties":{"weight":1}}},{"data":{"source":"com.fsck.k9.mailstore.migrations","target":"com.fsck.k9.controller","label":"depends","properties":{"weight":1}}},{"data":{"source":"com.fsck.k9.power","target":"com.fsck.k9.service","label":"depends","properties":{"weight":1}}},{"data":{"source":"com.fsck.k9.notification","target":"com.fsck.k9.service","label":"depends","properties":{"weight":1}}},{"data":{"source":"com.fsck.k9.message.extractors","target":"com.fsck.k9","label":"depends","properties":{"weight":1}}},{"data":{"source":"com.fsck.k9.fragment","target":"com.fsck.k9.mailstore","label":"depends","properties":{"weight":1}}},{"data":{"source":"com.fsck.k9.message.quote","target":"com.fsck.k9.helper","label":"depends","properties":{"weight":1}}},{"data":{"source":"com.fsck.k9.preferences","target":"com.fsck.k9.mailstore","label":"depends","properties":{"weight":1}}},{"data":{"source":"com.fsck.k9.controller","target":"com.fsck.k9.search","label":"depends","properties":{"weight":1}}},{"data":{"source":"com.fsck.k9.controller","target":"com.fsck.k9.mailstore","label":"depends","properties":{"weight":1}}},{"data":{"source":"com.fsck.k9.notification","target":"com.fsck.k9.search","label":"depends","properties":{"weight":1}}},{"data":{"source":"com.fsck.k9.activity.compose","target":"com.fsck.k9.helper","label":"depends","properties":{"weight":2}}},{"data":{"source":"com.fsck.k9.fragment","target":"com.fsck.k9.controller","label":"depends","properties":{"weight":2}}},{"data":{"source":"com.fsck.k9.ui.message","target":"com.fsck.k9.mailstore","label":"depends","properties":{"weight":1}}},{"data":{"source":"com.fsck.k9.ui.messageview","target":"com.fsck.k9.provider","label":"depends","properties":{"weight":1}}},{"data":{"source":"com.fsck.k9.activity","target":"com.fsck.k9.ui.message","label":"depends","properties":{"weight":1}}},{"data":{"source":"com.fsck.k9.provider","target":"com.fsck.k9.controller","label":"depends","properties":{"weight":1}}},{"data":{"source":"com.fsck.k9.helper","target":"com.fsck.k9.power","label":"depends","properties":{"weight":1}}},{"data":{"source":"com.fsck.k9.view","target":"com.fsck.k9","label":"depends","properties":{"weight":2}}},{"data":{"source":"com.fsck.k9","target":"com.fsck.k9.preferences","label":"depends","properties":{"weight":18}}},{"data":{"source":"com.fsck.k9.mailstore.migrations","target":"com.fsck.k9.preferences","label":"depends","properties":{"weight":1}}},{"data":{"source":"com.fsck.k9.message","target":"com.fsck.k9.message.html","label":"depends","properties":{"weight":1}}},{"data":{"source":"com.fsck.k9.activity.misc","target":"com.fsck.k9.helper","label":"depends","properties":{"weight":1}}}]}}